Metadata-Version: 2.1
Name: latticeflow-slicing
Version: 0.0.1
Summary: latticeflow-slicing package
Home-page: https://latticeflow.ai
Author: LatticeFlow Team
License: Proprietary
Platform: UNKNOWN
Classifier: License :: Other/Proprietary License
